{
  "slug": "matusiyumon",
  "name_ja": "マッシュモン",
  "stage_ja": "成長期",
  "attribute": null,
  "personality": null,
  "evolution_conditions": "エージェントランク1以上◆防御力200以上",
  "evolves_from": [
    "タネモン"
  ],
  "evolves_to": [
    "スカモン",
    "ナニモン",
    "ウッドモン",
    "フライモン"
  ],
  "main_image": "https://appmedia.jp/wp-content/themes/appmedia/lib/digimon_ts/img/タイムストレンジャー_図鑑_75.webp",
  "detail_url_ja": "https://appmedia.jp/digimon_ts/79298369",
  "sources": [
    "appmedia_jp"
  ],
  "match_type": "single_source",
  "confidence": 0.7,
  "name": "マッシュモン",
  "stage": "成長期",
  "name_en": "Matusiyumon"
}